LICENSE.txt
MANIFEST.in
README.rst
Tool.py
setup.py
abnertestlib/__init__.py
abnertestlib/abnerlibone.py
abnertestlib.egg-info/PKG-INFO
abnertestlib.egg-info/SOURCES.txt
abnertestlib.egg-info/dependency_links.txt
abnertestlib.egg-info/top_level.txt