Metadata-Version: 1.0
Name: abnertestlib
Version: 1.0.1
Summary: this is a niubi lib
Home-page: https://github.com
Author: ABNER
Author-email: 924770619@qq.com
License: MIT
Platform: UNKNOWN
